excode_distribution/Binomialdistribution.py
excode_distribution/Gaussiandistribution.py
excode_distribution/Generaldistribution.py
excode_distribution/__init__.py
excode_distribution-1.1.dist-info/DESCRIPTION.rst
excode_distribution-1.1.dist-info/METADATA
excode_distribution-1.1.dist-info/RECORD
excode_distribution-1.1.dist-info/WHEEL
excode_distribution-1.1.dist-info/metadata.json
excode_distribution-1.1.dist-info/top_level.txt
