Metadata-Version: 2.0
Name: excode-distribution
Version: 1.1
Summary: Gaussian and Binomial distribution
Home-page: UNKNOWN
Author: Opeyemi Oladipupo
Author-email: techrystein@gmail.com
License: UNKNOWN
Platform: UNKNOWN
